{"swagger":"2.0","info":{"title":"Azurewebsites","description":"API for ulrichfunction2.azurewebsites.net","version":"0.0.1"},"host":"ulrichfunction2.azurewebsites.net","schemes":["https"],"paths":{"/api/HttpTrigger1":{"get":{"tags":["Web"],"description":"Http trigger1","operationId":"HttpTrigger1","parameters":[{"name":"code","in":"query","description":"Code","required":false,"type":"string","x-example":"q76OkVnqUOfW6ELVCFCspNSg_qiryXQDcyomjaZk_a-8AzFu-PD3qQ"}],"responses":{"200":{"description":"OK"}},"security":[]}}},"definitions":{},"securityDefinitions":{},"security":[],"tags":[{"name":"Web","description":"Operations about Web"}]}